cleon-0.1.15.dist-info/METADATA
cleon-0.1.15.dist-info/WHEEL
cleon-0.1.15.dist-info/entry_points.txt
cleon/__init__.py
cleon/__main__.py
cleon/_cleon.abi3.so
cleon/_ladon.pyi
cleon/autoroute.py
cleon/backend.py
cleon/bin/cleon
cleon/cli.py
cleon/images/__init__.py
cleon/images/claude.png
cleon/images/codex-white.png
cleon/images/gemini.png
cleon/magic.py
cleon/oauth.py
cleon/py.typed
cleon/settings.py
cleon-0.1.15.dist-info/RECORD
