Metadata-Version: 2.4
Name: cleon
Version: 0.1.15
Classifier: License :: OSI Approved :: MIT License
Classifier: Programming Language :: Python :: 3
Classifier: Programming Language :: Python :: 3 :: Only
Classifier: Programming Language :: Python :: 3.9
Classifier: Programming Language :: Python :: 3.10
Classifier: Programming Language :: Python :: 3.11
Classifier: Programming Language :: Python :: 3.12
Requires-Dist: ipython>=8.0
Requires-Dist: websocket-client>=1.6
Requires-Dist: cleon-jupyter-extension>=0.1.0
Requires-Dist: jupyterlab>=4 ; extra == 'jupyter'
Provides-Extra: no-jupyter
Provides-Extra: jupyter
Summary: A Genetic Dynasty of Agentic Clones for Jupyter Notebooks
Keywords: codex,cleon,ipython
Author-email: Madhava Jay <me@madhavajay.com>
License: MIT
Requires-Python: >=3.9
Project-URL: Homepage, https://github.com/madhavajay/cleon
Project-URL: Repository, https://github.com/madhavajay/cleon
